{
  "$schema": "../gen/schemas/desktop-schema.json",
  "identifier": "app-windows",
  "description": "Window controls (drag + min/max/close) for locally-served app and document windows, so they can run borderless with a custom title bar.",
  "windows": ["doc-*", "app-*"],
  "remote": {
    "urls": ["http://127.0.0.1:*"]
  },
  "permissions": [
    "core:window:allow-start-dragging",
    "core:window:allow-minimize",
    "core:window:allow-maximize",
    "core:window:allow-unmaximize",
    "core:window:allow-toggle-maximize",
    "core:window:allow-is-maximized",
    "core:window:allow-close"
  ]
}
